fuzz_introspector/.gitignore
fuzz_introspector/__init__.py
fuzz_introspector/analysis.py
fuzz_introspector/cfg_load.py
fuzz_introspector/cli.py
fuzz_introspector/code_coverage.py
fuzz_introspector/commands.py
fuzz_introspector/constants.py
fuzz_introspector/data_loader.py
fuzz_introspector/debug_info.py
fuzz_introspector/diff_report.py
fuzz_introspector/exceptions.py
fuzz_introspector/html_constants.py
fuzz_introspector/html_helpers.py
fuzz_introspector/html_report.py
fuzz_introspector/json_report.py
fuzz_introspector/utils.py
fuzz_introspector/analyses/__init__.py
fuzz_introspector/analyses/annotated_cfg.py
fuzz_introspector/analyses/bug_digestor.py
fuzz_introspector/analyses/calltree_analysis.py
fuzz_introspector/analyses/driver_synthesizer.py
fuzz_introspector/analyses/engine_input.py
fuzz_introspector/analyses/far_reach_low_coverage_analyser.py
fuzz_introspector/analyses/filepath_analyser.py
fuzz_introspector/analyses/function_call_analyser.py
fuzz_introspector/analyses/metadata.py
fuzz_introspector/analyses/optimal_targets.py
fuzz_introspector/analyses/public_candidate_analyser.py
fuzz_introspector/analyses/runtime_coverage_analysis.py
fuzz_introspector/analyses/sinks_analyser.py
fuzz_introspector/analyses/source_code_line_analyser.py
fuzz_introspector/analyses/data/__init__.py
fuzz_introspector/analyses/data/cwe_data.py
fuzz_introspector/datatypes/__init__.py
fuzz_introspector/datatypes/branch_profile.py
fuzz_introspector/datatypes/bug.py
fuzz_introspector/datatypes/function_profile.py
fuzz_introspector/datatypes/fuzzer_profile.py
fuzz_introspector/datatypes/project_profile.py
fuzz_introspector/frontends/.gitignore
fuzz_introspector/frontends/__init__.py
fuzz_introspector/frontends/core.py
fuzz_introspector/frontends/datatypes.py
fuzz_introspector/frontends/frontend_c.py
fuzz_introspector/frontends/frontend_cpp.py
fuzz_introspector/frontends/frontend_go.py
fuzz_introspector/frontends/frontend_jvm.py
fuzz_introspector/frontends/frontend_rust.py
fuzz_introspector-0.1.8.dist-info/METADATA
fuzz_introspector-0.1.8.dist-info/WHEEL
fuzz_introspector-0.1.8.dist-info/entry_points.txt
fuzz_introspector-0.1.8.dist-info/top_level.txt
fuzz_introspector-0.1.8.dist-info/RECORD
